qa_qc_check/__init__.py
qa_qc_check/controller/__init__.py
qa_qc_check/controller/checks.json
qa_qc_check/controller/meta_data.py
qa_qc_check/controller/meta_data_extractor.py
qa_qc_check/controller/qa_qc.py
qa_qc_check/model/__init__.py
qa_qc_check/model/metadata_model.py
qa_qc_check/test/__init__.py
qa_qc_check/test/conftest.py
qa_qc_check/test/controller/__init__.py
qa_qc_check/test/controller/test_meta_data.py
qa_qc_check/test/controller/test_meta_data_extractor.py
qa_qc_check/test/controller/test_qa_qc.py
qa_qc_check/validator/__init__.py
qa_qc_check/validator/meta_data_validator.py
satelite/__init__.py
satelite/config.py
satelite/core/__init__.py
satelite/core/downloader.py
satelite/gdal/__init__.py
satelite/gdal/gdal_commands.py
satelite/models/__init__.py
satelite/models/s2_enum.py
satelite/raster/__init__.py
satelite/raster/raster.py
satelite/sentinel2/__init__.py
satelite/sentinel2/fetch_unique_tile_date.py
satelite/sentinel2/fetch_unique_tile_date_pystac.py
satelite/sentinel2/get_tiles.py
satelite/sentinel2/mosaic_same_bands.py
satelite/sentinel2/path_row_from_shp.py
satelite/sentinel2/s2_l1c_urls.py
satelite/sentinel2/s2_l2a_urls.py
satelite/sentinel2/band_stack/__init__.py
satelite/sentinel2/band_stack/generate_band_stack.py
satelite/sentinel2/indices/__init__.py
satelite/sentinel2/indices/general_indices.py
satelite/tests/__init__.py
satelite/tests/conftest.py
satelite/tests/sentinel2/__init__.py
satelite/tests/sentinel2/test_fetch_unique_tile_date.py
satelite/tests/sentinel2/test_fetch_unique_tile_date_pystac.py
satelite/tests/sentinel2/test_get_tile.py
satelite/tests/sentinel2/test_mosaic_same_bands.py
satelite/tests/sentinel2/test_s2_l1c_urls.py
satelite/tests/sentinel2/test_s2_l2a_urls.py
satelite/tests/sentinel2/test_validate.py
satelite/validators/__init__.py
satelite/validators/check_shape_of_rid.py
test_core_package-1.2.0.dist-info/LICENCE.txt
test_core_package-1.2.0.dist-info/METADATA
test_core_package-1.2.0.dist-info/WHEEL
test_core_package-1.2.0.dist-info/top_level.txt
test_core_package-1.2.0.dist-info/RECORD
