Metadata-Version: 2.1
Name: test-core-package
Version: 1.2.0
Summary: satsure core package
Author: Satsure
Author-email: kmstpm@email.com
License-File: LICENCE.txt
Requires-Dist: requests
Requires-Dist: fiona
Requires-Dist: pandas
Requires-Dist: pystac
Requires-Dist: python-dotenv
Requires-Dist: sqlalchemy
Requires-Dist: aiosignal ==1.3.1
Requires-Dist: async-timeout ==4.0.3
Requires-Dist: attrs ==23.2.0
Requires-Dist: boto3 ==1.34.94
Requires-Dist: botocore ==1.34.94
Requires-Dist: frozenlist ==1.4.1
Requires-Dist: idna ==3.7
Requires-Dist: jmespath ==1.0.1
Requires-Dist: multidict ==6.0.5
Requires-Dist: python-dateutil ==2.9.0.post0
Requires-Dist: s3transfer ==0.10.1
Requires-Dist: six ==1.16.0
Requires-Dist: urllib3 ==1.26.18
Requires-Dist: yarl ==1.9.4
Requires-Dist: awscli
Requires-Dist: gdal ==3.6.2
Requires-Dist: google-cloud-storage
Requires-Dist: pyproj
Requires-Dist: rasterstats
Requires-Dist: rasterio
Requires-Dist: wget
